docky/__init__.py
docky/main.py
docky/cmd/__init__.py
docky/cmd/base.py
docky/cmd/forward.py
docky/cmd/run_open.py
docky/common/__init__.py
docky/common/api.py
docky/common/project.py
docky-9.0.4.dist-info/licenses/LICENSE
docky-9.0.4.dist-info/METADATA
docky-9.0.4.dist-info/WHEEL
docky-9.0.4.dist-info/entry_points.txt
docky-9.0.4.dist-info/top_level.txt
docky-9.0.4.dist-info/RECORD
