Metadata-Version: 2.4
Name: docky
Version: 9.0.4
Summary: Make developpement with docker simply
Home-page: https://github.com/akretion/docky/
Author: Akretion
Author-email: contact@akretion.com
License: AGPLv3+
Classifier: Programming Language :: Python :: 3
Classifier: Operating System :: POSIX :: Linux
License-File: LICENSE
Requires-Dist: python-on-whales
Requires-Dist: plumbum
Requires-Dist: rainbow_logging_handler
Requires-Dist: python-slugify
Requires-Dist: requests
Requires-Dist: importlib-metadata
Requires-Dist: PyYAML>=6.0.1
Dynamic: author
Dynamic: author-email
Dynamic: classifier
Dynamic: description
Dynamic: home-page
Dynamic: license
Dynamic: license-file
Dynamic: requires-dist
Dynamic: summary
